odoo9_addon_web_widget_image_webcam-9.0.1.0.0-py2.7-nspkg.pth
odoo_addons/web_widget_image_webcam/__openerp__.py
odoo_addons/web_widget_image_webcam/__init__.py
odoo_addons/web_widget_image_webcam/README.rst
odoo_addons/web_widget_image_webcam/views/assets.xml
odoo_addons/web_widget_image_webcam/static/description/icon.png
odoo_addons/web_widget_image_webcam/static/src/img/webcam_placeholder.png
odoo_addons/web_widget_image_webcam/static/src/js/webcam_widget.js
odoo_addons/web_widget_image_webcam/static/src/js/webcam.js
odoo_addons/web_widget_image_webcam/static/src/js/webcam.swf
odoo_addons/web_widget_image_webcam/static/src/css/web_widget_image_webcam.css
odoo_addons/web_widget_image_webcam/static/src/xml/web_widget_image_webcam.xml
odoo9_addon_web_widget_image_webcam-9.0.1.0.0.dist-info/top_level.txt
odoo9_addon_web_widget_image_webcam-9.0.1.0.0.dist-info/WHEEL
odoo9_addon_web_widget_image_webcam-9.0.1.0.0.dist-info/RECORD
odoo9_addon_web_widget_image_webcam-9.0.1.0.0.dist-info/metadata.json
odoo9_addon_web_widget_image_webcam-9.0.1.0.0.dist-info/DESCRIPTION.rst
odoo9_addon_web_widget_image_webcam-9.0.1.0.0.dist-info/METADATA
odoo9_addon_web_widget_image_webcam-9.0.1.0.0.dist-info/namespace_packages.txt
