Metadata-Version: 2.0
Name: odoo9-addon-web-widget-image-webcam
Version: 9.0.1.0.0
Summary: Allows to take image with WebCam
Home-page: https://www.techreceptives.com
Author: UNKNOWN
Author-email: UNKNOWN
License: LGPL-3
Platform: UNKNOWN
Requires-Dist: odoo (<9.1a,>=9.0a)
Classifier: Programming Language :: Python :: 2.7
Classifier: Framework :: Odoo
Classifier: License :: OSI Approved :: GNU Lesser General Public License v3 (LGPLv3)
